py_chatbot_payload/__init__.py
py_chatbot_payload/facebook_chat.py
py_chatbot_payload/helpers.py
py_chatbot_payload/line_chat.py
py_chatbot_payload/payloads.py
py_chatbot_payload-0.0.2.dist-info/LICENSE
py_chatbot_payload-0.0.2.dist-info/METADATA
py_chatbot_payload-0.0.2.dist-info/WHEEL
py_chatbot_payload-0.0.2.dist-info/top_level.txt
py_chatbot_payload-0.0.2.dist-info/RECORD
