Metadata-Version: 2.1
Name: py-chatbot-payload
Version: 0.0.2
Summary: A package to create a payload for chatbot platforms
Home-page: https://github.com/e23thr/py-chatbot-response
Author: Praphan Oranphanlert
Author-email: e23thr@gmail.com
License: UNKNOWN
Platform: UNKNOWN
Classifier: Programming Language :: Python :: 3
Classifier: License :: OSI Approved :: MIT License
Classifier: Operating System :: OS Independent
Requires-Python: >=3.6
